D_FF.v
`timescale 1ns/1ps
// D flip-flop: negative-edge clock, asynchronous active-high reset
module D_FF(q, d, clk, reset);
    output q;
    input  d, clk, reset;
    reg    q;

    always @(posedge reset or negedge clk)
        if (reset)
            q = 1'b0;
        else
            q = d;
endmodule

T_FF.v
`timescale 1ns/1ps
// T flip-flop built from a D flip-flop and an inverter
module T_FF(q, clk, reset);
    output q;
    input  clk, reset;
    wire   d;

    D_FF dff0(q, d, clk, reset);
    not  n1(d, q);          // not is a Verilog primitive; D = ~Q makes it toggle
endmodule

ripple_carry_counter.v
`timescale 1ns/1ps
// Top block: 4-bit ripple carry counter
module ripple_carry_counter(q, clk, reset);
    output [3:0] q;
    input        clk, reset;

    // 4 instances of the T flip-flop; each is clocked by the previous stage's q
    T_FF tff0(q[0], clk,  reset);
    T_FF tff1(q[1], q[0], reset);
    T_FF tff2(q[2], q[1], reset);
    T_FF tff3(q[3], q[2], reset);
endmodule

stimulus.v
`timescale 1ns/1ps
// Stimulus block (testbench): drives clk and reset, prints q
module stimulus;
    reg        clk;
    reg        reset;
    wire [3:0] q;

    // instantiate the design block
    ripple_carry_counter r1(q, clk, reset);

    // clock: toggles every 5 ns (period 10 ns)
    initial clk = 1'b0;
    always #5 clk = ~clk;

    // control reset
    initial begin
        reset = 1'b1;       // reset the counter
        #15 reset = 1'b0;   // release reset, counting starts
        #180 reset = 1'b1;  // reset again mid-count
        #10 reset = 1'b0;
        #20 $finish;
    end

    // waveform dump (for GTKWave) and console monitor
    initial begin
        $dumpfile("dump.vcd");
        $dumpvars(0, stimulus);
    end
    initial $monitor($time, " Output q = %d", q);
endmodule

dump.vcd
$date
	Sun Sep 20 19:14:30 2026
$end
$version
	Icarus Verilog
$end
$timescale
	1ps
$end
$scope module stimulus $end
$var wire 4 ! q [3:0] $end
$var reg 1 " clk $end
$var reg 1 # reset $end
$scope module r1 $end
$var wire 1 " clk $end
$var wire 1 # reset $end
$var wire 4 $ q [3:0] $end
$scope module tff0 $end
$var wire 1 " clk $end
$var wire 1 % d $end
$var wire 1 # reset $end
$var wire 1 & q $end
$scope module dff0 $end
$var wire 1 " clk $end
$var wire 1 % d $end
$var wire 1 # reset $end
$var reg 1 & q $end
$upscope $end
$upscope $end
$scope module tff1 $end
$var wire 1 ' clk $end
$var wire 1 ( d $end
$var wire 1 # reset $end
$var wire 1 ) q $end
$scope module dff0 $end
$var wire 1 ' clk $end
$var wire 1 ( d $end
$var wire 1 # reset $end
$var reg 1 ) q $end
$upscope $end
$upscope $end
$scope module tff2 $end
$var wire 1 * clk $end
$var wire 1 + d $end
$var wire 1 # reset $end
$var wire 1 , q $end
$scope module dff0 $end
$var wire 1 * clk $end
$var wire 1 + d $end
$var wire 1 # reset $end
$var reg 1 , q $end
$upscope $end
$upscope $end
$scope module tff3 $end
$var wire 1 - clk $end
$var wire 1 . d $end
$var wire 1 # reset $end
$var wire 1 / q $end
$scope module dff0 $end
$var wire 1 - clk $end
$var wire 1 . d $end
$var wire 1 # reset $end
$var reg 1 / q $end
$upscope $end
$upscope $end
$upscope $end
$upscope $end
$enddefinitions $end
$comment Show the parameter values. $end
$dumpall
$end
#0
$dumpvars
0/
1.
0-
0,
1+
0*
0)
1(
0'
0&
1%
b0 $
1#
0"
b0 !
$end
#5000
1"
#10000
0"
#15000
1"
0#
#20000
0%
1'
b1 !
b1 $
1&
0"
#25000
1"
#30000
0(
1*
1)
1%
0'
b10 !
b10 $
0&
0"
#35000
1"
#40000
0%
1'
b11 !
b11 $
1&
0"
#45000
1"
#50000
0+
1-
1,
1(
0*
0)
1%
0'
b100 !
b100 $
0&
0"
#55000
1"
#60000
0%
1'
b101 !
b101 $
1&
0"
#65000
1"
#70000
0(
1*
1)
1%
0'
b110 !
b110 $
0&
0"
#75000
1"
#80000
0%
1'
b111 !
b111 $
1&
0"
#85000
1"
#90000
0.
1/
1+
0-
0,
1(
0*
0)
1%
0'
b1000 !
b1000 $
0&
0"
#95000
1"
#100000
0%
1'
b1001 !
b1001 $
1&
0"
#105000
1"
#110000
0(
1*
1)
1%
0'
b1010 !
b1010 $
0&
0"
#115000
1"
#120000
0%
1'
b1011 !
b1011 $
1&
0"
#125000
1"
#130000
0+
1-
1,
1(
0*
0)
1%
0'
b1100 !
b1100 $
0&
0"
#135000
1"
#140000
0%
1'
b1101 !
b1101 $
1&
0"
#145000
1"
#150000
0(
1*
1)
1%
0'
b1110 !
b1110 $
0&
0"
#155000
1"
#160000
0%
1'
b1111 !
b1111 $
1&
0"
#165000
1"
#170000
1.
0/
1+
0-
0,
1(
0*
0)
1%
0'
b0 !
b0 $
0&
0"
#175000
1"
#180000
0%
1'
b1 !
b1 $
1&
0"
#185000
1"
#190000
0(
1*
1)
1%
0'
b10 !
b10 $
0&
0"
#195000
1(
0*
b0 !
b0 $
0)
1"
1#
#200000
0"
#205000
1"
0#
#210000
0%
1'
b1 !
b1 $
1&
0"
#215000
1"
#220000
0(
1*
1)
1%
0'
b10 !
b10 $
0&
0"
